{
  "parties": [
    "Centrack International, a Florida corporation (\"the Customer\")",
    "i-on interactive"
  ],
  "effective_date": null,
  "governing_law": "Florida",
  "payment_terms": null,
  "termination_clause": {
    "text": "TERMINATION\n\nThe term of this Agreement for the Hosted Site shall commence upon April 1, 1999 and shall continue for a period of six (6) months, unless earlier terminated in accordance with provisions hereof. This Agreement shall automatically be renewed for one (1) or more one (1) month periods unless either the Customer or i-on gives notice to the other party of its intention not to renew the\n\n4 Agreement, which notice must be given not less than fifteen (15) days before the end of the respective initial or renewal term.\n\nEither party may terminate this Agreement without cause at any time effective upon thirty (30) days' written notice. Notwithstanding anything to the contrary contained in this Agreement, no termination of this Agreement for any reason whatsoever shall relieve the Customer of the o",
    "start": 10350,
    "end": 11161,
    "confidence": 0.72,
    "source": "regex"
  },
  "_doc_id": "CENTRACKINTERNATIONALINC_10_29_1999-EX-10.3-WEB SITE HOSTING AGREEMENT.txt",
  "_char_count": 15176,
  "_provenance": {
    "governing_law": {
      "source": "spacy"
    }
  }
}